orthopy/__init__.py
orthopy/helpers.py
orthopy/c1/__init__.py
orthopy/c1/associated_legendre.py
orthopy/c1/chebyshev1.py
orthopy/c1/chebyshev2.py
orthopy/c1/gegenbauer.py
orthopy/c1/jacobi.py
orthopy/c1/legendre.py
orthopy/c1/tools.py
orthopy/cn/__init__.py
orthopy/cn/main.py
orthopy/cn/tools.py
orthopy/e1r/__init__.py
orthopy/e1r/main.py
orthopy/e1r/tools.py
orthopy/e1r2/__init__.py
orthopy/e1r2/main.py
orthopy/e1r2/tools.py
orthopy/enr2/__init__.py
orthopy/enr2/main.py
orthopy/enr2/tools.py
orthopy/s2/__init__.py
orthopy/s2/tools.py
orthopy/s2/xu.py
orthopy/s2/zernike.py
orthopy/s2/zernike2.py
orthopy/t2/__init__.py
orthopy/t2/main.py
orthopy/t2/tools.py
orthopy/tools/__init__.py
orthopy/tools/generate_rc.py
orthopy/u3/__init__.py
orthopy/u3/main.py
orthopy/u3/tools.py
orthopy_gpl-0.9.5.dist-info/LICENSE.txt
orthopy_gpl-0.9.5.dist-info/METADATA
orthopy_gpl-0.9.5.dist-info/WHEEL
orthopy_gpl-0.9.5.dist-info/top_level.txt
orthopy_gpl-0.9.5.dist-info/RECORD
