Metadata-Version: 2.1
Name: orthopy-gpl
Version: 0.9.5
Summary: The last GPL version of orthopy, published as is
Home-page: https://zenodo.org/record/5751934
Author: Nico Schlömer
Author-email: nico.schloemer@gmail.com
Maintainer: Aleksei Gerasimov
Maintainer-email: ger-alex@seznam.cz
License: GPL-3.0-or-later
Project-URL: PyPI, https://pypi.org/project/orthopy/
Project-URL: GitHub, https://github.com/nschloe/orthopy
Platform: UNKNOWN
Classifier: Development Status :: 4 - Beta
Classifier: Intended Audience :: Science/Research
Classifier: License :: OSI Approved :: GNU General Public License v3 or later (GPLv3+)
Classifier: Operating System :: OS Independent
Classifier: Programming Language :: Python
Classifier: Programming Language :: Python :: 3
Classifier: Programming Language :: Python :: 3.7
Classifier: Programming Language :: Python :: 3.8
Classifier: Programming Language :: Python :: 3.9
Classifier: Programming Language :: Python :: 3.10
Classifier: Topic :: Scientific/Engineering
Classifier: Topic :: Scientific/Engineering :: Mathematics
Requires-Python: >=3.7
License-File: LICENSE.txt
Requires-Dist: numpy
Requires-Dist: sympy
Requires-Dist: typing-extensions ; python_version < "3.8"
Provides-Extra: all
Requires-Dist: cplot ; extra == 'all'
Requires-Dist: matplotlib ; extra == 'all'
Requires-Dist: matplotx ; extra == 'all'
Requires-Dist: meshio ; extra == 'all'
Requires-Dist: meshzoo ; extra == 'all'
Provides-Extra: disk-plot
Requires-Dist: meshzoo ; extra == 'disk-plot'
Provides-Extra: plot
Requires-Dist: matplotlib ; extra == 'plot'
Requires-Dist: matplotx ; extra == 'plot'
Provides-Extra: sphere-plot
Requires-Dist: cplot ; extra == 'sphere-plot'
Requires-Dist: meshio ; extra == 'sphere-plot'
Requires-Dist: meshzoo ; extra == 'sphere-plot'
